src/__init__.py
src/pypkgfreeze.py
pypkgfreeze-0.1.4.dist-info/LICENSE
pypkgfreeze-0.1.4.dist-info/METADATA
pypkgfreeze-0.1.4.dist-info/WHEEL
pypkgfreeze-0.1.4.dist-info/entry_points.txt
pypkgfreeze-0.1.4.dist-info/top_level.txt
pypkgfreeze-0.1.4.dist-info/RECORD
