Metadata-Version: 2.1
Name: pypkgfreeze
Version: 0.1.4
Summary: Automatically inserts your currently used package versions to setup.py.
Home-page: https://github.com/adamgold/pypkgfreeze
Author: Adam Goldschmidt
Author-email: adamgold7@gmail.com
License: BSD
Platform: UNKNOWN
Classifier: Programming Language :: Python :: 3
Classifier: Programming Language :: Python :: 3.6
Classifier: Environment :: Console
Classifier: Operating System :: OS Independent
Classifier: License :: OSI Approved :: BSD License
Requires-Dist: Click (==7.0)
Provides-Extra: test
Requires-Dist: pytest (==5.2.2) ; extra == 'test'
